{
  "timestamp": 1715351700,
  "tasks": [
    {
      "id": "dashboard_verification",
      "status": "SUCCESS",
      "details": "Directorios creados, dependencias instaladas con legacy-peer-deps, y todos los archivos .tsx/.ts generados correctamente mediante el script de inicialización seguro."
    },
    {
      "id": "schema_extraction",
      "status": "SUCCESS",
      "details": "Extraído el esquema de axyntrax.db restaurado desde data/, guardado en schema_local.json."
    },
    {
      "id": "sql_migration",
      "status": "SUCCESS",
      "details": "Generado migration_supabase.sql traduciendo SQLite a PostgreSQL, incluyendo las 5 tablas gerenciales adicionales."
    },
    {
      "id": "installation_scripts",
      "status": "SUCCESS",
      "details": "Creados los archivos public/modules/modulo1_automatizacion.bat, modulo2_reportes.bat, modulo3_comunicacion.bat con validación de key."
    },
    {
      "id": "documentation",
      "status": "SUCCESS",
      "details": "Generado SYSTEM_STATUS.md con el resumen ejecutivo del ecosistema."
    }
  ],
  "bridge_active": true,
  "waiting_for_user_credentials": true
}
